nbwavedrom/__init__.py
nbwavedrom-1.0.1.dist-info/LICENSE.txt
nbwavedrom-1.0.1.dist-info/WHEEL
nbwavedrom-1.0.1.dist-info/METADATA
nbwavedrom-1.0.1.dist-info/RECORD
