Metadata-Version: 2.1
Name: nbwavedrom
Version: 1.0.1
Summary: Wavedrom timing diagrams for Jupyter Notebook
Home-page: https://github.com/witchard/nbwavedrom
License: MIT
Keywords: wavedrom,jupyter,notebook
Author: witchard
Author-email: witchard@hotmail.co.uk
Requires-Python: >=3.5,<4.0
Classifier: Development Status :: 4 - Beta
Classifier: Framework :: Jupyter
Classifier: Framework :: Jupyter :: JupyterLab
Classifier: Intended Audience :: Developers
Classifier: Intended Audience :: Science/Research
Classifier: License :: OSI Approved :: MIT License
Classifier: Programming Language :: Python
Classifier: Programming Language :: Python :: 3
Classifier: Programming Language :: Python :: 3.5
Classifier: Programming Language :: Python :: 3.6
Classifier: Programming Language :: Python :: 3.7
Classifier: Programming Language :: Python :: 3.8
Classifier: Programming Language :: Python :: 3.9
Project-URL: Repository, https://github.com/witchard/nbwavedrom
